{
  "apiVersion": "dashboard.grafana.app/v2",
  "kind": "Dashboard",
  "metadata": {
    "name": "P_6sFISWz",
    "namespace": "default",
    "uid": "WPIo61XEpnmNM2ErUICxTtPpOdECuuBpDDxXHgudUc0X",
    "resourceVersion": "1770300160000006",
    "generation": 1,
    "creationTimestamp": "2026-02-05T14:02:47Z",
    "labels": {
      "grafana.app/deprecatedInternalID": "20"
    },
    "annotations": {
      "grafana.app/createdBy": "provisioning:",
      "grafana.app/managedBy": "classic-file-provisioning",
      "grafana.app/managerId": "default",
      "grafana.app/sourceChecksum": "8a30c37c33383fc2658bcaec9fb0f1e5",
      "grafana.app/sourcePath": "energy.json",
      "grafana.app/sourceTimestamp": "1",
      "grafana.app/updatedBy": "provisioning:",
      "grafana.app/updatedTimestamp": "2026-02-05T14:02:47Z",
      "grafana.app/folder": ""
    }
  },
  "spec": {
    "annotations": [
      {
        "kind": "AnnotationQuery",
        "spec": {
          "query": {
            "kind": "DataQuery",
            "group": "datasource",
            "version": "v0",
            "datasource": {
              "name": "grafana"
            },
            "spec": {
              "limit": 100,
              "matchAny": false,
              "tags": [],
              "type": "dashboard"
            }
          },
          "enable": true,
          "hide": true,
          "iconColor": "rgba(0, 211, 255, 1)",
          "name": "Annotations & Alerts",
          "builtIn": true,
          "legacyOptions": {
            "$$hashKey": "object:7",
            "type": "dashboard"
          }
        }
      }
    ],
    "cursorSync": "Off",
    "editable": true,
    "elements": {
      "panel-10": {
        "kind": "Panel",
        "spec": {
          "id": 10,
          "title": "Apparent power",
          "description": "",
          "links": [],
          "data": {
            "kind": "QueryGroup",
            "spec": {
              "queries": [
                {
                  "kind": "PanelQuery",
                  "spec": {
                    "query": {
                      "kind": "DataQuery",
                      "group": "prometheus",
                      "version": "v0",
                      "datasource": {
                        "name": "prometheus"
                      },
                      "spec": {
                        "exemplar": true,
                        "expr": "snmp_upsAdvOutputApparentPower",
                        "interval": "",
                        "legendFormat": "{{hostname}}"
                      }
                    },
                    "refId": "A",
                    "hidden": false
                  }
                }
              ],
              "transformations": [],
              "queryOptions": {}
            }
          },
          "vizConfig": {
            "kind": "VizConfig",
            "group": "timeseries",
            "version": "12.0.5",
            "spec": {
              "options": {
                "legend": {
                  "calcs": [],
                  "displayMode": "list",
                  "placement": "bottom",
                  "showLegend": true
                },
                "tooltip": {
                  "hideZeros": false,
                  "mode": "multi",
                  "sort": "none"
                }
              },
              "fieldConfig": {
                "defaults": {
                  "unit": "voltamp",
                  "thresholds": {
                    "mode": "absolute",
                    "steps": [
                      {
                        "value": null,
                        "color": "green"
                      },
                      {
                        "value": 80,
                        "color": "red"
                      }
                    ]
                  },
                  "color": {
                    "mode": "palette-classic"
                  },
                  "custom": {
                    "axisBorderShow": false,
                    "axisCenteredZero": false,
                    "axisColorMode": "text",
                    "axisLabel": "",
                    "axisPlacement": "auto",
                    "barAlignment": 0,
                    "barWidthFactor": 0.6,
                    "drawStyle": "line",
                    "fillOpacity": 10,
                    "gradientMode": "none",
                    "hideFrom": {
                      "legend": false,
                      "tooltip": false,
                      "viz": false
                    },
                    "insertNulls": false,
                    "lineInterpolation": "linear",
                    "lineWidth": 1,
                    "pointSize": 5,
                    "scaleDistribution": {
                      "type": "linear"
                    },
                    "showPoints": "never",
                    "spanNulls": 600000,
                    "stacking": {
                      "group": "A",
                      "mode": "none"
                    },
                    "thresholdsStyle": {
                      "mode": "off"
                    }
                  }
                },
                "overrides": []
              }
            }
          }
        }
      },
      "panel-12": {
        "kind": "Panel",
        "spec": {
          "id": 12,
          "title": "Battery capacity remaining",
          "description": "",
          "links": [],
          "data": {
            "kind": "QueryGroup",
            "spec": {
              "queries": [
                {
                  "kind": "PanelQuery",
                  "spec": {
                    "query": {
                      "kind": "DataQuery",
                      "group": "prometheus",
                      "version": "v0",
                      "datasource": {
                        "name": "prometheus"
                      },
                      "spec": {
                        "exemplar": true,
                        "expr": "snmp_upsHighPrecBatteryCapacity",
                        "interval": "",
                        "legendFormat": "{{hostname}}"
                      }
                    },
                    "refId": "B",
                    "hidden": false
                  }
                },
                {
                  "kind": "PanelQuery",
                  "spec": {
                    "query": {
                      "kind": "DataQuery",
                      "group": "prometheus",
                      "version": "v0",
                      "datasource": {
                        "name": "prometheus"
                      },
                      "spec": {
                        "exemplar": true,
                        "expr": "snmp_upsEstimatedChargeRemaining",
                        "interval": "",
                        "legendFormat": "{{hostname}}"
                      }
                    },
                    "refId": "D",
                    "hidden": false
                  }
                }
              ],
              "transformations": [],
              "queryOptions": {}
            }
          },
          "vizConfig": {
            "kind": "VizConfig",
            "group": "timeseries",
            "version": "12.0.5",
            "spec": {
              "options": {
                "legend": {
                  "calcs": [],
                  "displayMode": "list",
                  "placement": "bottom",
                  "showLegend": true
                },
                "tooltip": {
                  "hideZeros": false,
                  "mode": "multi",
                  "sort": "none"
                }
              },
              "fieldConfig": {
                "defaults": {
                  "unit": "percent",
                  "min": 0,
                  "thresholds": {
                    "mode": "absolute",
                    "steps": [
                      {
                        "value": null,
                        "color": "green"
                      },
                      {
                        "value": 80,
                        "color": "red"
                      }
                    ]
                  },
                  "color": {
                    "mode": "palette-classic"
                  },
                  "custom": {
                    "axisBorderShow": false,
                    "axisCenteredZero": false,
                    "axisColorMode": "text",
                    "axisLabel": "capacity",
                    "axisPlacement": "auto",
                    "barAlignment": 0,
                    "barWidthFactor": 0.6,
                    "drawStyle": "line",
                    "fillOpacity": 10,
                    "gradientMode": "none",
                    "hideFrom": {
                      "legend": false,
                      "tooltip": false,
                      "viz": false
                    },
                    "insertNulls": false,
                    "lineInterpolation": "linear",
                    "lineWidth": 1,
                    "pointSize": 5,
                    "scaleDistribution": {
                      "type": "linear"
                    },
                    "showPoints": "never",
                    "spanNulls": 600000,
                    "stacking": {
                      "group": "A",
                      "mode": "none"
                    },
                    "thresholdsStyle": {
                      "mode": "off"
                    }
                  }
                },
                "overrides": []
              }
            }
          }
        }
      },
      "panel-14": {
        "kind": "Panel",
        "spec": {
          "id": 14,
          "title": "Battery runtime remaining",
          "description": "",
          "links": [],
          "data": {
            "kind": "QueryGroup",
            "spec": {
              "queries": [
                {
                  "kind": "PanelQuery",
                  "spec": {
                    "query": {
                      "kind": "DataQuery",
                      "group": "prometheus",
                      "version": "v0",
                      "datasource": {
                        "name": "prometheus"
                      },
                      "spec": {
                        "exemplar": true,
                        "expr": "snmp_upsAdvBatteryRunTimeRemaining / 100",
                        "interval": "",
                        "legendFormat": "{{hostname}}"
                      }
                    },
                    "refId": "A",
                    "hidden": false
                  }
                },
                {
                  "kind": "PanelQuery",
                  "spec": {
                    "query": {
                      "kind": "DataQuery",
                      "group": "prometheus",
                      "version": "v0",
                      "datasource": {
                        "name": "prometheus"
                      },
                      "spec": {
                        "exemplar": true,
                        "expr": "snmp_upsEstimatedMinutesRemaining * 60",
                        "interval": "",
                        "legendFormat": "{{hostname}}"
                      }
                    },
                    "refId": "C",
                    "hidden": false
                  }
                }
              ],
              "transformations": [],
              "queryOptions": {}
            }
          },
          "vizConfig": {
            "kind": "VizConfig",
            "group": "timeseries",
            "version": "12.0.5",
            "spec": {
              "options": {
                "legend": {
                  "calcs": [],
                  "displayMode": "list",
                  "placement": "bottom",
                  "showLegend": true
                },
                "tooltip": {
                  "hideZeros": false,
                  "mode": "multi",
                  "sort": "none"
                }
              },
              "fieldConfig": {
                "defaults": {
                  "unit": "s",
                  "min": 0,
                  "thresholds": {
                    "mode": "absolute",
                    "steps": [
                      {
                        "value": null,
                        "color": "green"
                      }
                    ]
                  },
                  "color": {
                    "mode": "palette-classic"
                  },
                  "custom": {
                    "axisBorderShow": false,
                    "axisCenteredZero": false,
                    "axisColorMode": "text",
                    "axisLabel": "runtime",
                    "axisPlacement": "auto",
                    "barAlignment": 0,
                    "barWidthFactor": 0.6,
                    "drawStyle": "line",
                    "fillOpacity": 10,
                    "gradientMode": "none",
                    "hideFrom": {
                      "legend": false,
                      "tooltip": false,
                      "viz": false
                    },
                    "insertNulls": false,
                    "lineInterpolation": "linear",
                    "lineWidth": 1,
                    "pointSize": 5,
                    "scaleDistribution": {
                      "type": "linear"
                    },
                    "showPoints": "never",
                    "spanNulls": 600000,
                    "stacking": {
                      "group": "A",
                      "mode": "none"
                    },
                    "thresholdsStyle": {
                      "mode": "off"
                    }
                  }
                },
                "overrides": []
              }
            }
          }
        }
      },
      "panel-15": {
        "kind": "Panel",
        "spec": {
          "id": 15,
          "title": "Frequency",
          "description": "",
          "links": [],
          "data": {
            "kind": "QueryGroup",
            "spec": {
              "queries": [
                {
                  "kind": "PanelQuery",
                  "spec": {
                    "query": {
                      "kind": "DataQuery",
                      "group": "prometheus",
                      "version": "v0",
                      "datasource": {
                        "name": "prometheus"
                      },
                      "spec": {
                        "editorMode": "code",
                        "exemplar": true,
                        "expr": "homeassistant_sensor_frequency_hz > 0",
                        "interval": "",
                        "legendFormat": "{{friendly_name}}",
                        "range": true
                      }
                    },
                    "refId": "A",
                    "hidden": false
                  }
                },
                {
                  "kind": "PanelQuery",
                  "spec": {
                    "query": {
                      "kind": "DataQuery",
                      "group": "prometheus",
                      "version": "v0",
                      "datasource": {
                        "name": "prometheus"
                      },
                      "spec": {
                        "editorMode": "code",
                        "exemplar": true,
                        "expr": "snmp_upsHighPrecOutputFrequency",
                        "interval": "",
                        "legendFormat": "{{hostname}} output",
                        "range": true
                      }
                    },
                    "refId": "B",
                    "hidden": false
                  }
                },
                {
                  "kind": "PanelQuery",
                  "spec": {
                    "query": {
                      "kind": "DataQuery",
                      "group": "prometheus",
                      "version": "v0",
                      "datasource": {
                        "name": "prometheus"
                      },
                      "spec": {
                        "editorMode": "code",
                        "exemplar": true,
                        "expr": "snmp_upsHighPrecInputFrequency",
                        "interval": "",
                        "legendFormat": "{{hostname}} input",
                        "range": true
                      }
                    },
                    "refId": "C",
                    "hidden": false
                  }
                }
              ],
              "transformations": [],
              "queryOptions": {}
            }
          },
          "vizConfig": {
            "kind": "VizConfig",
            "group": "timeseries",
            "version": "12.0.5",
            "spec": {
              "options": {
                "legend": {
                  "calcs": [],
                  "displayMode": "list",
                  "placement": "bottom",
                  "showLegend": true
                },
                "tooltip": {
                  "hideZeros": false,
                  "mode": "multi",
                  "sort": "none"
                }
              },
              "fieldConfig": {
                "defaults": {
                  "unit": "rothz",
                  "thresholds": {
                    "mode": "absolute",
                    "steps": [
                      {
                        "value": null,
                        "color": "green"
                      },
                      {
                        "value": 80,
                        "color": "red"
                      }
                    ]
                  },
                  "color": {
                    "mode": "palette-classic"
                  },
                  "custom": {
                    "axisBorderShow": false,
                    "axisCenteredZero": false,
                    "axisColorMode": "text",
                    "axisLabel": "",
                    "axisPlacement": "auto",
                    "barAlignment": 0,
                    "barWidthFactor": 0.6,
                    "drawStyle": "line",
                    "fillOpacity": 0,
                    "gradientMode": "none",
                    "hideFrom": {
                      "legend": false,
                      "tooltip": false,
                      "viz": false
                    },
                    "insertNulls": false,
                    "lineInterpolation": "linear",
                    "lineWidth": 1,
                    "pointSize": 5,
                    "scaleDistribution": {
                      "type": "linear"
                    },
                    "showPoints": "never",
                    "spanNulls": 600000,
                    "stacking": {
                      "group": "A",
                      "mode": "none"
                    },
                    "thresholdsStyle": {
                      "mode": "off"
                    }
                  }
                },
                "overrides": []
              }
            }
          }
        }
      },
      "panel-2": {
        "kind": "Panel",
        "spec": {
          "id": 2,
          "title": "Active power",
          "description": "",
          "links": [],
          "data": {
            "kind": "QueryGroup",
            "spec": {
              "queries": [
                {
                  "kind": "PanelQuery",
                  "spec": {
                    "query": {
                      "kind": "DataQuery",
                      "group": "prometheus",
                      "version": "v0",
                      "datasource": {
                        "name": "prometheus"
                      },
                      "spec": {
                        "editorMode": "code",
                        "exemplar": true,
                        "expr": "homeassistant_sensor_power_w{friendly_name=~\"((Dori|Wizzy) PC) Power\"}",
                        "interval": "",
                        "legendFormat": "{{friendly_name}} [Socket]",
                        "range": true
                      }
                    },
                    "refId": "A",
                    "hidden": false
                  }
                },
                {
                  "kind": "PanelQuery",
                  "spec": {
                    "query": {
                      "kind": "DataQuery",
                      "group": "prometheus",
                      "version": "v0",
                      "datasource": {
                        "name": "prometheus"
                      },
                      "spec": {
                        "exemplar": true,
                        "expr": "snmp_upsAdvOutputActivePower",
                        "interval": "",
                        "legendFormat": "{{hostname}} [UPS]"
                      }
                    },
                    "refId": "B",
                    "hidden": false
                  }
                },
                {
                  "kind": "PanelQuery",
                  "spec": {
                    "query": {
                      "kind": "DataQuery",
                      "group": "prometheus",
                      "version": "v0",
                      "datasource": {
                        "name": "prometheus"
                      },
                      "spec": {
                        "exemplar": true,
                        "expr": "snmp_upsOutputPercentLoad{hostname=\"ups-office\"} * (1000 / 100)",
                        "interval": "",
                        "legendFormat": "{{hostname}} [UPS]"
                      }
                    },
                    "refId": "C",
                    "hidden": false
                  }
                },
                {
                  "kind": "PanelQuery",
                  "spec": {
                    "query": {
                      "kind": "DataQuery",
                      "group": "prometheus",
                      "version": "v0",
                      "datasource": {
                        "name": "prometheus"
                      },
                      "spec": {
                        "editorMode": "code",
                        "exemplar": true,
                        "expr": "homeassistant_sensor_power_w{friendly_name=~\"Hot phase (left|right) .*\"}",
                        "interval": "",
                        "legendFormat": "{{friendly_name}} [Panel]",
                        "range": true
                      }
                    },
                    "refId": "D",
                    "hidden": false
                  }
                },
                {
                  "kind": "PanelQuery",
                  "spec": {
                    "query": {
                      "kind": "DataQuery",
                      "group": "prometheus",
                      "version": "v0",
                      "datasource": {
                        "name": "prometheus"
                      },
                      "spec": {
                        "editorMode": "code",
                        "exemplar": true,
                        "expr": "sum(homeassistant_sensor_power_w{friendly_name=~\"Hot phase (left|right) .*\"})",
                        "interval": "",
                        "legendFormat": "Hot phase both [Panel]",
                        "range": true
                      }
                    },
                    "refId": "E",
                    "hidden": false
                  }
                }
              ],
              "transformations": [],
              "queryOptions": {}
            }
          },
          "vizConfig": {
            "kind": "VizConfig",
            "group": "timeseries",
            "version": "12.0.5",
            "spec": {
              "options": {
                "legend": {
                  "calcs": [],
                  "displayMode": "list",
                  "placement": "bottom",
                  "showLegend": true
                },
                "tooltip": {
                  "hideZeros": false,
                  "mode": "multi",
                  "sort": "none"
                }
              },
              "fieldConfig": {
                "defaults": {
                  "unit": "watt",
                  "thresholds": {
                    "mode": "absolute",
                    "steps": [
                      {
                        "value": null,
                        "color": "green"
                      },
                      {
                        "value": 80,
                        "color": "red"
                      }
                    ]
                  },
                  "color": {
                    "mode": "palette-classic"
                  },
                  "custom": {
                    "axisBorderShow": false,
                    "axisCenteredZero": false,
                    "axisColorMode": "text",
                    "axisLabel": "",
                    "axisPlacement": "auto",
                    "barAlignment": 0,
                    "barWidthFactor": 0.6,
                    "drawStyle": "line",
                    "fillOpacity": 10,
                    "gradientMode": "none",
                    "hideFrom": {
                      "legend": false,
                      "tooltip": false,
                      "viz": false
                    },
                    "insertNulls": false,
                    "lineInterpolation": "linear",
                    "lineWidth": 1,
                    "pointSize": 5,
                    "scaleDistribution": {
                      "type": "linear"
                    },
                    "showPoints": "never",
                    "spanNulls": 600000,
                    "stacking": {
                      "group": "A",
                      "mode": "none"
                    },
                    "thresholdsStyle": {
                      "mode": "off"
                    }
                  }
                },
                "overrides": []
              }
            }
          }
        }
      },
      "panel-4": {
        "kind": "Panel",
        "spec": {
          "id": 4,
          "title": "Voltage",
          "description": "",
          "links": [],
          "data": {
            "kind": "QueryGroup",
            "spec": {
              "queries": [
                {
                  "kind": "PanelQuery",
                  "spec": {
                    "query": {
                      "kind": "DataQuery",
                      "group": "prometheus",
                      "version": "v0",
                      "datasource": {
                        "name": "prometheus"
                      },
                      "spec": {
                        "exemplar": true,
                        "expr": "homeassistant_sensor_voltage_v > 0",
                        "interval": "",
                        "legendFormat": "{{friendly_name}}"
                      }
                    },
                    "refId": "A",
                    "hidden": false
                  }
                },
                {
                  "kind": "PanelQuery",
                  "spec": {
                    "query": {
                      "kind": "DataQuery",
                      "group": "prometheus",
                      "version": "v0",
                      "datasource": {
                        "name": "prometheus"
                      },
                      "spec": {
                        "exemplar": true,
                        "expr": "snmp_upsHighPrecOutputVoltage",
                        "interval": "",
                        "legendFormat": "{{hostname}} output"
                      }
                    },
                    "refId": "B",
                    "hidden": false
                  }
                },
                {
                  "kind": "PanelQuery",
                  "spec": {
                    "query": {
                      "kind": "DataQuery",
                      "group": "prometheus",
                      "version": "v0",
                      "datasource": {
                        "name": "prometheus"
                      },
                      "spec": {
                        "exemplar": true,
                        "expr": "snmp_upsHighPrecInputLineVoltage",
                        "interval": "",
                        "legendFormat": "{{hostname}} input"
                      }
                    },
                    "refId": "C",
                    "hidden": false
                  }
                }
              ],
              "transformations": [],
              "queryOptions": {}
            }
          },
          "vizConfig": {
            "kind": "VizConfig",
            "group": "timeseries",
            "version": "12.0.5",
            "spec": {
              "options": {
                "legend": {
                  "calcs": [],
                  "displayMode": "list",
                  "placement": "bottom",
                  "showLegend": true
                },
                "tooltip": {
                  "hideZeros": false,
                  "mode": "multi",
                  "sort": "none"
                }
              },
              "fieldConfig": {
                "defaults": {
                  "unit": "volt",
                  "min": 115,
                  "max": 125,
                  "thresholds": {
                    "mode": "absolute",
                    "steps": [
                      {
                        "value": null,
                        "color": "green"
                      },
                      {
                        "value": 80,
                        "color": "red"
                      }
                    ]
                  },
                  "color": {
                    "mode": "palette-classic"
                  },
                  "custom": {
                    "axisBorderShow": false,
                    "axisCenteredZero": false,
                    "axisColorMode": "text",
                    "axisLabel": "",
                    "axisPlacement": "auto",
                    "barAlignment": 0,
                    "barWidthFactor": 0.6,
                    "drawStyle": "line",
                    "fillOpacity": 0,
                    "gradientMode": "none",
                    "hideFrom": {
                      "legend": false,
                      "tooltip": false,
                      "viz": false
                    },
                    "insertNulls": false,
                    "lineInterpolation": "linear",
                    "lineWidth": 1,
                    "pointSize": 5,
                    "scaleDistribution": {
                      "type": "linear"
                    },
                    "showPoints": "never",
                    "spanNulls": 600000,
                    "stacking": {
                      "group": "A",
                      "mode": "none"
                    },
                    "thresholdsStyle": {
                      "mode": "off"
                    }
                  }
                },
                "overrides": []
              }
            }
          }
        }
      },
      "panel-6": {
        "kind": "Panel",
        "spec": {
          "id": 6,
          "title": "Current",
          "description": "",
          "links": [],
          "data": {
            "kind": "QueryGroup",
            "spec": {
              "queries": [
                {
                  "kind": "PanelQuery",
                  "spec": {
                    "query": {
                      "kind": "DataQuery",
                      "group": "prometheus",
                      "version": "v0",
                      "datasource": {
                        "name": "prometheus"
                      },
                      "spec": {
                        "exemplar": true,
                        "expr": "snmp_upsHighPrecOutputCurrent",
                        "interval": "",
                        "legendFormat": "{{hostname}}"
                      }
                    },
                    "refId": "A",
                    "hidden": false
                  }
                },
                {
                  "kind": "PanelQuery",
                  "spec": {
                    "query": {
                      "kind": "DataQuery",
                      "group": "prometheus",
                      "version": "v0",
                      "datasource": {
                        "name": "prometheus"
                      },
                      "spec": {
                        "editorMode": "code",
                        "expr": "homeassistant_sensor_current_a",
                        "legendFormat": "{{friendly_name}}",
                        "range": true
                      }
                    },
                    "refId": "B",
                    "hidden": false
                  }
                }
              ],
              "transformations": [],
              "queryOptions": {}
            }
          },
          "vizConfig": {
            "kind": "VizConfig",
            "group": "timeseries",
            "version": "12.0.5",
            "spec": {
              "options": {
                "legend": {
                  "calcs": [],
                  "displayMode": "list",
                  "placement": "bottom",
                  "showLegend": true
                },
                "tooltip": {
                  "hideZeros": false,
                  "mode": "multi",
                  "sort": "none"
                }
              },
              "fieldConfig": {
                "defaults": {
                  "unit": "amp",
                  "thresholds": {
                    "mode": "absolute",
                    "steps": [
                      {
                        "value": null,
                        "color": "green"
                      },
                      {
                        "value": 80,
                        "color": "red"
                      }
                    ]
                  },
                  "color": {
                    "mode": "palette-classic"
                  },
                  "custom": {
                    "axisBorderShow": false,
                    "axisCenteredZero": false,
                    "axisColorMode": "text",
                    "axisLabel": "",
                    "axisPlacement": "auto",
                    "barAlignment": 0,
                    "barWidthFactor": 0.6,
                    "drawStyle": "line",
                    "fillOpacity": 10,
                    "gradientMode": "none",
                    "hideFrom": {
                      "legend": false,
                      "tooltip": false,
                      "viz": false
                    },
                    "insertNulls": false,
                    "lineInterpolation": "linear",
                    "lineWidth": 1,
                    "pointSize": 5,
                    "scaleDistribution": {
                      "type": "linear"
                    },
                    "showPoints": "never",
                    "spanNulls": 600000,
                    "stacking": {
                      "group": "A",
                      "mode": "none"
                    },
                    "thresholdsStyle": {
                      "mode": "off"
                    }
                  }
                },
                "overrides": []
              }
            }
          }
        }
      },
      "panel-8": {
        "kind": "Panel",
        "spec": {
          "id": 8,
          "title": "Efficiency",
          "description": "",
          "links": [],
          "data": {
            "kind": "QueryGroup",
            "spec": {
              "queries": [
                {
                  "kind": "PanelQuery",
                  "spec": {
                    "query": {
                      "kind": "DataQuery",
                      "group": "prometheus",
                      "version": "v0",
                      "datasource": {
                        "name": "prometheus"
                      },
                      "spec": {
                        "exemplar": true,
                        "expr": "snmp_upsHighPrecOutputEfficiency",
                        "interval": "",
                        "intervalFactor": 1,
                        "legendFormat": "{{hostname}}"
                      }
                    },
                    "refId": "A",
                    "hidden": false
                  }
                }
              ],
              "transformations": [],
              "queryOptions": {}
            }
          },
          "vizConfig": {
            "kind": "VizConfig",
            "group": "timeseries",
            "version": "12.0.5",
            "spec": {
              "options": {
                "legend": {
                  "calcs": [],
                  "displayMode": "list",
                  "placement": "bottom",
                  "showLegend": true
                },
                "tooltip": {
                  "hideZeros": false,
                  "mode": "multi",
                  "sort": "none"
                }
              },
              "fieldConfig": {
                "defaults": {
                  "unit": "percent",
                  "min": 0,
                  "max": 100,
                  "thresholds": {
                    "mode": "absolute",
                    "steps": [
                      {
                        "value": null,
                        "color": "green"
                      },
                      {
                        "value": 80,
                        "color": "red"
                      }
                    ]
                  },
                  "color": {
                    "mode": "palette-classic"
                  },
                  "custom": {
                    "axisBorderShow": false,
                    "axisCenteredZero": false,
                    "axisColorMode": "text",
                    "axisLabel": "",
                    "axisPlacement": "auto",
                    "barAlignment": 0,
                    "barWidthFactor": 0.6,
                    "drawStyle": "line",
                    "fillOpacity": 0,
                    "gradientMode": "none",
                    "hideFrom": {
                      "legend": false,
                      "tooltip": false,
                      "viz": false
                    },
                    "insertNulls": false,
                    "lineInterpolation": "linear",
                    "lineWidth": 1,
                    "pointSize": 5,
                    "scaleDistribution": {
                      "type": "linear"
                    },
                    "showPoints": "never",
                    "spanNulls": true,
                    "stacking": {
                      "group": "A",
                      "mode": "none"
                    },
                    "thresholdsStyle": {
                      "mode": "off"
                    }
                  }
                },
                "overrides": []
              }
            }
          }
        }
      }
    },
    "layout": {
      "kind": "GridLayout",
      "spec": {
        "items": [
          {
            "kind": "GridLayoutItem",
            "spec": {
              "x": 0,
              "y": 0,
              "width": 12,
              "height": 8,
              "element": {
                "kind": "ElementReference",
                "name": "panel-2"
              }
            }
          },
          {
            "kind": "GridLayoutItem",
            "spec": {
              "x": 12,
              "y": 0,
              "width": 12,
              "height": 8,
              "element": {
                "kind": "ElementReference",
                "name": "panel-4"
              }
            }
          },
          {
            "kind": "GridLayoutItem",
            "spec": {
              "x": 0,
              "y": 8,
              "width": 12,
              "height": 8,
              "element": {
                "kind": "ElementReference",
                "name": "panel-12"
              }
            }
          },
          {
            "kind": "GridLayoutItem",
            "spec": {
              "x": 12,
              "y": 8,
              "width": 12,
              "height": 8,
              "element": {
                "kind": "ElementReference",
                "name": "panel-14"
              }
            }
          },
          {
            "kind": "GridLayoutItem",
            "spec": {
              "x": 0,
              "y": 16,
              "width": 12,
              "height": 8,
              "element": {
                "kind": "ElementReference",
                "name": "panel-8"
              }
            }
          },
          {
            "kind": "GridLayoutItem",
            "spec": {
              "x": 12,
              "y": 16,
              "width": 12,
              "height": 8,
              "element": {
                "kind": "ElementReference",
                "name": "panel-6"
              }
            }
          },
          {
            "kind": "GridLayoutItem",
            "spec": {
              "x": 0,
              "y": 24,
              "width": 12,
              "height": 8,
              "element": {
                "kind": "ElementReference",
                "name": "panel-10"
              }
            }
          },
          {
            "kind": "GridLayoutItem",
            "spec": {
              "x": 12,
              "y": 24,
              "width": 12,
              "height": 8,
              "element": {
                "kind": "ElementReference",
                "name": "panel-15"
              }
            }
          }
        ]
      }
    },
    "links": [],
    "liveNow": false,
    "preload": false,
    "tags": [],
    "timeSettings": {
      "from": "now-6h",
      "to": "now",
      "autoRefresh": "",
      "autoRefreshIntervals": [
        "5s",
        "10s",
        "30s",
        "1m",
        "5m",
        "15m",
        "30m",
        "1h",
        "2h",
        "1d"
      ],
      "hideTimepicker": false,
      "fiscalYearStartMonth": 0
    },
    "title": "Energy",
    "variables": []
  }
}